MANIFEST.in
setup.py
src/impaf_formskit.egg-info/PKG-INFO
src/impaf_formskit.egg-info/SOURCES.txt
src/impaf_formskit.egg-info/dependency_links.txt
src/impaf_formskit.egg-info/namespace_packages.txt
src/impaf_formskit.egg-info/not-zip-safe
src/impaf_formskit.egg-info/requires.txt
src/impaf_formskit.egg-info/top_level.txt
src/implugin/__init__.py
src/implugin/formskit/__init__.py
src/implugin/formskit/controller.py
src/implugin/formskit/models.py
src/implugin/formskit/testing.py
src/implugin/formskit/widget.py
src/implugin/formskit/templates/begin.jinja2
src/implugin/formskit/templates/combobox.jinja2
src/implugin/formskit/templates/end.jinja2
src/implugin/formskit/templates/field_error.jinja2
src/implugin/formskit/templates/form_error.jinja2
src/implugin/formskit/templates/hidden.jinja2
src/implugin/formskit/templates/password.jinja2
src/implugin/formskit/templates/select.jinja2
src/implugin/formskit/templates/submit.jinja2
src/implugin/formskit/templates/text.jinja2
src/implugin/formskit/tests/__init__.py
src/implugin/formskit/tests/test_controller.py
src/implugin/formskit/tests/test_models.py
src/implugin/formskit/tests/test_widget.py