Metadata-Version: 1.0
Name: impaf-formskit
Version: 0.1.3
Summary: Formskit plugin for Impaf.
Home-page: UNKNOWN
Author: UNKNOWN
Author-email: UNKNOWN
License: Apache License 2.0
Platform: UNKNOWN
